{"legislative_session": "194th", "identifier": "HD5661", "title": "The annual report of the Executive Office for Housing and Livable Communities (under Section 27 1/2 of Chapter 23B of the General Laws) submitting its HousingWorks Infrastructure annual report for the fiscal years 2024 and 2025", "from_organization": "~{\"classification\": \"lower\"}", "classification": ["proposed bill"], "subject": [], "abstracts": [], "other_titles": [], "other_identifiers": [{"identifier": "ocd-bill-ma-194th-hd5661"}], "actions": [{"description": "Placed on file", "date": "2026-02-19", "organization_id": "~{\"classification\": \"lower\"}", "classification": [], "related_entities": []}], "sponsorships": [{"name": "Executive Office of Housing and Livable Communities", "classification": "primary", "entity_type": "organization", "primary": true, "person_id": null, "organization_id": "~{\"name\": \"Executive Office of Housing and Livable Communities\"}"}], "related_bills": [], "versions": [{"note": "Bill Text", "links": [{"url": "https://malegislature.gov/Bills/194/HD5661.pdf", "media_type": "application/pdf"}], "date": "", "classification": ""}], "documents": [], "citations": [], "sources": [{"url": "https://malegislature.gov/Bills/194/HD5661", "note": ""}], "extras": {}, "jurisdiction": {"id": "ocd-jurisdiction/country:us/state:ma/government", "name": "Massachusetts", "classification": "state", "division_id": "ocd-division/country:us/state:ma"}, "scraped_at": "2026-07-13T22:37:00+00:00", "_id": "5c63031a-7f0b-11f1-aa88-e6eb2c01712e"}