{"legislative_session": "194th", "identifier": "SD3382", "title": "Order considering House Bill, No. 4206 during the Senate Session of November 19, 2025", "from_organization": "~{\"classification\": \"upper\"}", "classification": ["proposed bill"], "subject": [], "abstracts": [{"note": "summary", "abstract": "Senate, November 13, 2025 -- Order (Senator Rodrigues) relative to considering House Bill, No. 4206 during the Senate Session of November 19, 2025"}], "other_titles": [], "other_identifiers": [], "actions": [{"description": "Rules suspended and adopted", "date": "2025-11-13", "organization_id": "~{\"classification\": \"upper\"}", "classification": [], "related_entities": []}], "sponsorships": [{"name": "Michael J. Rodrigues", "classification": "primary", "entity_type": "person", "primary": true, "person_id": "~{\"name\": \"Michael J. Rodrigues\"}", "organization_id": null}], "related_bills": [], "versions": [{"note": "Bill Text", "links": [{"url": "https://malegislature.gov/Bills/194/SD3382.pdf", "media_type": "application/pdf"}], "date": "", "classification": ""}], "documents": [], "citations": [], "sources": [{"url": "https://malegislature.gov/Bills/194/SD3382", "note": ""}], "extras": {}, "jurisdiction": {"id": "ocd-jurisdiction/country:us/state:ma/government", "name": "Massachusetts", "classification": "state", "division_id": "ocd-division/country:us/state:ma"}, "scraped_at": "2026-01-13T09:47:20+00:00", "_id": "da619eb0-f064-11f0-800b-8ee3d43e4288"}