{"legislative_session": "194th", "identifier": "HD5506", "title": "The annual report of the Massachusetts Gaming Commission (under Section 71 of Chapter 23K and Section 23 of Chapter 23N of the General Laws) submitting its summary of key findings and recommendations from the fiscal year 2025 research agenda", "from_organization": "~{\"classification\": \"lower\"}", "classification": ["proposed bill"], "subject": [], "abstracts": [], "other_titles": [], "other_identifiers": [{"identifier": "ocd-bill-ma-194th-hd5506"}], "actions": [{"description": "Placed on file", "date": "2026-01-12", "organization_id": "~{\"classification\": \"lower\"}", "classification": [], "related_entities": []}], "sponsorships": [{"name": "Massachusetts Gaming Commission", "classification": "primary", "entity_type": "organization", "primary": true, "person_id": null, "organization_id": "~{\"name\": \"Massachusetts Gaming Commission\"}"}], "related_bills": [], "versions": [{"note": "Bill Text", "links": [{"url": "https://malegislature.gov/Bills/194/HD5506.pdf", "media_type": "application/pdf"}], "date": "", "classification": ""}], "documents": [], "citations": [], "sources": [{"url": "https://malegislature.gov/Bills/194/HD5506", "note": ""}], "extras": {}, "jurisdiction": {"id": "ocd-jurisdiction/country:us/state:ma/government", "name": "Massachusetts", "classification": "state", "division_id": "ocd-division/country:us/state:ma"}, "scraped_at": "2026-07-06T14:33:52+00:00", "_id": "b58c6da6-7947-11f1-9e04-eeb03528ce7e"}