{"legislative_session": "194th", "identifier": "S2800", "title": "An act regulating the sale of hemp products to protect public health", "from_organization": "~{\"classification\": \"upper\"}", "classification": ["bill"], "subject": [], "abstracts": [{"note": "summary", "abstract": "Senate, January 8, 2025 -- The committee on Agriculture and Fisheries to whom was referred the petition (accompanied by bill, Senate, No. 54) of Joanne M. Comerford for legislation to regulate the sale of hemp products and establish the Hemp Product Education Fund, report the accompanying bill (Senate, No. 2800)."}], "other_titles": [], "other_identifiers": [{"identifier": "ocd-bill-ma-194th-s2800"}], "actions": [{"description": "Reported from the committee on Agriculture and Fisheries", "date": "2026-01-08", "organization_id": "~{\"classification\": \"upper\"}", "classification": [], "related_entities": []}, {"description": "New draft of S54", "date": "2026-01-08", "organization_id": "~{\"classification\": \"upper\"}", "classification": [], "related_entities": []}, {"description": "Bill reported favorably by committee and referred to the committee on Senate Ways and Means", "date": "2026-01-08", "organization_id": "~{\"classification\": \"upper\"}", "classification": ["committee-passage-favorable", "referral-committee"], "related_entities": [{"name": "the committee on Senate Ways and Means", "entity_type": "organization", "organization_id": null}, {"name": "committee on Senate Ways and Means", "entity_type": "organization", "organization_id": null}]}], "sponsorships": [{"name": "Joint Committee on Agriculture and Fisheries", "classification": "primary", "entity_type": "organization", "primary": true, "person_id": null, "organization_id": "~{\"name\": \"Joint Committee on Agriculture and Fisheries\"}"}, {"name": "Joanne M. Comerford", "classification": "cosponsor", "entity_type": "person", "primary": false, "person_id": "~{\"name\": \"Joanne M. Comerford\"}", "organization_id": null}], "related_bills": [], "versions": [{"note": "Bill Text", "links": [{"url": "https://malegislature.gov/Bills/194/S2800.pdf", "media_type": "application/pdf"}], "date": "", "classification": ""}], "documents": [], "citations": [], "sources": [{"url": "https://malegislature.gov/Bills/194/S2800", "note": ""}], "extras": {}, "jurisdiction": {"id": "ocd-jurisdiction/country:us/state:ma/government", "name": "Massachusetts", "classification": "state", "division_id": "ocd-division/country:us/state:ma"}, "scraped_at": "2026-07-06T18:52:06+00:00", "_id": "c8891b24-796b-11f1-9e04-eeb03528ce7e"}