{"legislative_session": "194th", "identifier": "S3175", "title": "An Act protecting children from addictive social media feeds", "from_organization": "~{\"classification\": \"upper\"}", "classification": ["bill"], "subject": [], "abstracts": [{"note": "summary", "abstract": "Senate, July 9, 2026 -- Text of the Senate Bill protecting children from addictive social media feeds (Senate, No. 3175) (being the text of Senate, No. 3164, printed as amended)"}], "other_titles": [], "other_identifiers": [{"identifier": "ocd-bill-ma-194th-s3175"}], "actions": [{"description": "S3164 reprinted, as amended", "date": "2026-07-09", "organization_id": "~{\"classification\": \"upper\"}", "classification": [], "related_entities": []}, {"description": "Passed to be engrossed -see   Roll Call #206 (Yeas 38 to Nays 2)", "date": "2026-07-09", "organization_id": "~{\"classification\": \"upper\"}", "classification": ["passage"], "related_entities": []}], "sponsorships": [{"name": "Cynthia Stone Creem", "classification": "cosponsor", "entity_type": "person", "primary": false, "person_id": "~{\"name\": \"Cynthia Stone Creem\"}", "organization_id": null}], "related_bills": [], "versions": [{"note": "Bill Text", "links": [{"url": "https://malegislature.gov/Bills/194/S3175.pdf", "media_type": "application/pdf"}], "date": "", "classification": ""}], "documents": [], "citations": [], "sources": [{"url": "https://malegislature.gov/Bills/194/S3175", "note": ""}], "extras": {}, "jurisdiction": {"id": "ocd-jurisdiction/country:us/state:ma/government", "name": "Massachusetts", "classification": "state", "division_id": "ocd-division/country:us/state:ma"}, "scraped_at": "2026-07-15T15:12:32+00:00", "_id": "99c2e748-805f-11f1-9784-12bdef9859f0"}