{"legislative_session": "194th", "identifier": "H5361", "title": "Study Order", "from_organization": "~{\"classification\": \"lower\"}", "classification": ["bill"], "subject": [], "abstracts": [{"note": "summary", "abstract": "Order relative to authorizing the committee on Labor and Workforce Development to make an investigation and study of certain House documents relative to worker compensation and work hours"}], "other_titles": [], "other_identifiers": [{"identifier": "ocd-bill-ma-194th-h5361"}], "actions": [{"description": "Reported from the committee on Labor and Workforce Development", "date": "2026-04-15", "organization_id": "~{\"classification\": \"lower\"}", "classification": [], "related_entities": []}, {"description": "Accompanied by H2067, H2128, H2131, H2133 and H2182", "date": "2026-04-15", "organization_id": "~{\"classification\": \"lower\"}", "classification": [], "related_entities": []}, {"description": "Order reported favorably by committee and referred to the committee on Joint Rules", "date": "2026-04-15", "organization_id": "~{\"classification\": \"lower\"}", "classification": ["committee-passage-favorable", "referral-committee"], "related_entities": [{"name": "committee on Joint Rules", "entity_type": "organization", "organization_id": null}, {"name": "the committee on Joint Rules", "entity_type": "organization", "organization_id": null}]}, {"description": "Discharged to the committee on House Rules", "date": "2026-04-15", "organization_id": "~{\"classification\": \"lower\"}", "classification": ["referral-committee"], "related_entities": [{"name": "House Rules", "entity_type": "organization", "organization_id": null}]}], "sponsorships": [{"name": "Joint Committee on Labor and Workforce Development", "classification": "primary", "entity_type": "organization", "primary": true, "person_id": null, "organization_id": "~{\"name\": \"Joint Committee on Labor and Workforce Development\"}"}], "related_bills": [], "versions": [{"note": "Bill Text", "links": [{"url": "https://malegislature.gov/Bills/194/H5361.pdf", "media_type": "application/pdf"}], "date": "", "classification": ""}], "documents": [], "citations": [], "sources": [{"url": "https://malegislature.gov/Bills/194/H5361", "note": ""}], "extras": {}, "jurisdiction": {"id": "ocd-jurisdiction/country:us/state:ma/government", "name": "Massachusetts", "classification": "state", "division_id": "ocd-division/country:us/state:ma"}, "scraped_at": "2026-07-02T00:26:28+00:00", "_id": "aa6ab160-75ac-11f1-8ff5-96e4a8870bcc"}