{"legislative_session": "194th", "identifier": "H5464", "title": "An Act relative to real estate transfer fees and senior property tax relief in the city of Boston", "from_organization": "~{\"classification\": \"lower\"}", "classification": ["bill"], "subject": [], "abstracts": [{"note": "summary", "abstract": "By Representative Fluker-Reid of Boston, a petition (accompanied by bill, House, No. 5464) of Brandy Fluker-Reid (with the approval of the mayor and city council) relative to real estate transfer fees and senior property tax relief in the city of Boston.  Revenue.  [Local Approval Received.]"}], "other_titles": [], "other_identifiers": [{"identifier": "ocd-bill-ma-194th-h5464"}], "actions": [{"description": "Referred to the committee on Revenue", "date": "2026-05-28", "organization_id": "~{\"classification\": \"lower\"}", "classification": ["referral-committee"], "related_entities": [{"name": "the committee on Revenue", "entity_type": "organization", "organization_id": null}, {"name": "committee on Revenue", "entity_type": "organization", "organization_id": null}]}], "sponsorships": [{"name": "Brandy Fluker-Reid", "classification": "primary", "entity_type": "person", "primary": true, "person_id": "~{\"name\": \"Brandy Fluker-Reid\"}", "organization_id": null}], "related_bills": [{"identifier": "HD 6170", "legislative_session": "194th", "relation_type": "replaces"}], "versions": [{"note": "Bill Text", "links": [{"url": "https://malegislature.gov/Bills/194/H5464.pdf", "media_type": "application/pdf"}], "date": "", "classification": ""}], "documents": [], "citations": [], "sources": [{"url": "https://malegislature.gov/Bills/194/H5464", "note": ""}], "extras": {}, "jurisdiction": {"id": "ocd-jurisdiction/country:us/state:ma/government", "name": "Massachusetts", "classification": "state", "division_id": "ocd-division/country:us/state:ma"}, "scraped_at": "2026-07-15T10:47:50+00:00", "_id": "9f84d44a-803a-11f1-9784-12bdef9859f0"}