{"legislative_session": "194th", "identifier": "HD5657", "title": "A report of the Massachusetts Office of Victim Assistance (MOVA) (under item 0840-0100 of Section 2 of Chapter 9 of the Acts of 2025) submitting the Victim and Witness Assistance Board report relative to the Massachusetts Victims of Violent Crimes Compensation program", "from_organization": "~{\"classification\": \"lower\"}", "classification": ["proposed bill"], "subject": [], "abstracts": [], "other_titles": [], "other_identifiers": [{"identifier": "ocd-bill-ma-194th-hd5657"}], "actions": [{"description": "Placed on file", "date": "2026-02-17", "organization_id": "~{\"classification\": \"lower\"}", "classification": [], "related_entities": []}], "sponsorships": [{"name": "Massachusetts Office for Victim Assistance", "classification": "primary", "entity_type": "organization", "primary": true, "person_id": null, "organization_id": "~{\"name\": \"Massachusetts Office for Victim Assistance\"}"}], "related_bills": [], "versions": [{"note": "Bill Text", "links": [{"url": "https://malegislature.gov/Bills/194/HD5657.pdf", "media_type": "application/pdf"}], "date": "", "classification": ""}], "documents": [], "citations": [], "sources": [{"url": "https://malegislature.gov/Bills/194/HD5657", "note": ""}], "extras": {}, "jurisdiction": {"id": "ocd-jurisdiction/country:us/state:ma/government", "name": "Massachusetts", "classification": "state", "division_id": "ocd-division/country:us/state:ma"}, "scraped_at": "2026-07-15T10:21:59+00:00", "_id": "0318c812-8037-11f1-9784-12bdef9859f0"}