{"legislative_session": "194th", "identifier": "S2863", "title": "An Act regarding the instruction of lifesaving skills in schools", "from_organization": "~{\"classification\": \"upper\"}", "classification": ["bill"], "subject": [], "abstracts": [{"note": "summary", "abstract": "The committee on Education, to whom was referred the petitions (accompanied by bill, Senate, No. 382) of John F. Keenan, Dylan A. Fernandes, Adam Gomez, Sal N. DiDomenico and other members of the General Court for legislation to require opioid use disorder education in public schools; (accompanied by bill, Senate, No. 413) of Mark C. Montigny for legislation to save lives through increased fentanyl awareness, aka Andrew's Law; (accompanied by bill, Senate, No. 432) of Jacob R. Oliveira for legislation relative to prescription opioid abuse prevention education; (accompanied by bill, Senate, No. 433) of Pavel M. Payano for legislation relative to substance use education in public schools; (accompanied by bill, Senate, No. 447) of Michael F. Rush for legislation to provide hands only CPR training and the use of defibrillators; and (accompanied by bill, Senate, No. 456) of Bruce E. Tarr, Madeleine Elizabeth Jackman , Patrick M. O'Connor, Shirley B. Arriaga and others relative to requiring instruction in cardiopulmonary resuscitation and the use of defibrillators for high school graduation, report the accompanying bill (Senate, No. 2863)."}], "other_titles": [], "other_identifiers": [{"identifier": "ocd-bill-ma-194th-s2863"}], "actions": [{"description": "Reported from the committee on Education", "date": "2025-12-15", "organization_id": "~{\"classification\": \"upper\"}", "classification": [], "related_entities": []}, {"description": "New draft of S382, S413, S432, S433, S447 and S456", "date": "2025-12-15", "organization_id": "~{\"classification\": \"upper\"}", "classification": [], "related_entities": []}, {"description": "Bill reported favorably by committee and referred to the committee on Senate Ways and Means", "date": "2025-12-15", "organization_id": "~{\"classification\": \"upper\"}", "classification": ["committee-passage-favorable", "referral-committee"], "related_entities": [{"name": "the committee on Senate Ways and Means", "entity_type": "organization", "organization_id": null}, {"name": "committee on Senate Ways and Means", "entity_type": "organization", "organization_id": null}]}], "sponsorships": [{"name": "Joint Committee on Education", "classification": "primary", "entity_type": "organization", "primary": true, "person_id": null, "organization_id": "~{\"name\": \"Joint Committee on Education\"}"}, {"name": "Michael F. Rush", "classification": "cosponsor", "entity_type": "person", "primary": false, "person_id": "~{\"name\": \"Michael F. Rush\"}", "organization_id": null}, {"name": "Sal N. DiDomenico", "classification": "cosponsor", "entity_type": "person", "primary": false, "person_id": "~{\"name\": \"Sal N. DiDomenico\"}", "organization_id": null}, {"name": "James B. Eldridge", "classification": "cosponsor", "entity_type": "person", "primary": false, "person_id": "~{\"name\": \"James B. Eldridge\"}", "organization_id": null}], "related_bills": [], "versions": [{"note": "Bill Text", "links": [{"url": "https://malegislature.gov/Bills/194/S2863.pdf", "media_type": "application/pdf"}], "date": "", "classification": ""}], "documents": [], "citations": [], "sources": [{"url": "https://malegislature.gov/Bills/194/S2863", "note": ""}], "extras": {}, "jurisdiction": {"id": "ocd-jurisdiction/country:us/state:ma/government", "name": "Massachusetts", "classification": "state", "division_id": "ocd-division/country:us/state:ma"}, "scraped_at": "2026-07-06T18:55:14+00:00", "_id": "386c5bb8-796c-11f1-9e04-eeb03528ce7e"}