{"legislative_session": "194th", "identifier": "H5174", "title": "An Act  to increase student access to career technical education schools and programs which are aligned with regional labor market needs", "from_organization": "~{\"classification\": \"lower\"}", "classification": ["bill"], "subject": [], "abstracts": [], "other_titles": [], "other_identifiers": [{"identifier": "ocd-bill-ma-194th-h5174"}], "actions": [{"description": "Reported from the committee on Education", "date": "2026-03-05", "organization_id": "~{\"classification\": \"lower\"}", "classification": [], "related_entities": []}, {"description": "New draft of H631", "date": "2026-03-05", "organization_id": "~{\"classification\": \"lower\"}", "classification": [], "related_entities": []}, {"description": "Bill reported favorably by committee and referred to the committee on House Ways and Means", "date": "2026-03-05", "organization_id": "~{\"classification\": \"lower\"}", "classification": ["committee-passage-favorable", "referral-committee"], "related_entities": [{"name": "committee on House Ways and Means", "entity_type": "organization", "organization_id": null}, {"name": "the committee on House Ways and Means", "entity_type": "organization", "organization_id": null}]}], "sponsorships": [{"name": "Joint Committee on Education", "classification": "primary", "entity_type": "organization", "primary": true, "person_id": null, "organization_id": "~{\"name\": \"Joint Committee on Education\"}"}, {"name": "Kate Lipper-Garabedian", "classification": "cosponsor", "entity_type": "person", "primary": false, "person_id": "~{\"name\": \"Kate Lipper-Garabedian\"}", "organization_id": null}, {"name": "Jessica Ann Giannino", "classification": "cosponsor", "entity_type": "person", "primary": false, "person_id": "~{\"name\": \"Jessica Ann Giannino\"}", "organization_id": null}], "related_bills": [], "versions": [{"note": "Bill Text", "links": [{"url": "https://malegislature.gov/Bills/194/H5174.pdf", "media_type": "application/pdf"}], "date": "", "classification": ""}], "documents": [], "citations": [], "sources": [{"url": "https://malegislature.gov/Bills/194/H5174", "note": ""}], "extras": {}, "jurisdiction": {"id": "ocd-jurisdiction/country:us/state:ma/government", "name": "Massachusetts", "classification": "state", "division_id": "ocd-division/country:us/state:ma"}, "scraped_at": "2026-07-13T22:38:12+00:00", "_id": "8781f830-7f0b-11f1-aa88-e6eb2c01712e"}