{"legislative_session": "194th", "identifier": "H5429", "title": "An Act providing injured on duty compensation to Chelmsford firefighter Nicholas Spinale", "from_organization": "~{\"classification\": \"lower\"}", "classification": ["bill"], "subject": [], "abstracts": [], "other_titles": [], "other_identifiers": [{"identifier": "ocd-bill-ma-194th-h5429"}], "actions": [{"description": "Referred to the committee on Public Service", "date": "2026-05-14", "organization_id": "~{\"classification\": \"lower\"}", "classification": ["referral-committee"], "related_entities": [{"name": "the committee on Public Service", "entity_type": "organization", "organization_id": null}, {"name": "committee on Public Service", "entity_type": "organization", "organization_id": null}]}, {"description": "Senate concurred", "date": "2026-05-18", "organization_id": "~{\"classification\": \"upper\"}", "classification": [], "related_entities": []}, {"description": "Hearing scheduled for 06/03/2026 from 11:00 AM-04:00 PM in B-2", "date": "2026-05-22", "organization_id": "~{\"classification\": \"legislature\"}", "classification": [], "related_entities": []}, {"description": "Hearing rescheduled to 06/03/2026 from 11:00 AM-11:45 AM in B-2                                                  Hearing updated to New End Time", "date": "2026-06-03", "organization_id": "~{\"classification\": \"legislature\"}", "classification": [], "related_entities": []}, {"description": "Bill reported favorably by committee and referred to the committee on House Ways and Means", "date": "2026-06-29", "organization_id": "~{\"classification\": \"lower\"}", "classification": ["committee-passage-favorable", "referral-committee"], "related_entities": [{"name": "committee on House Ways and Means", "entity_type": "organization", "organization_id": null}, {"name": "the committee on House Ways and Means", "entity_type": "organization", "organization_id": null}]}], "sponsorships": [{"name": "Maura T. Healey", "classification": "primary", "entity_type": "organization", "primary": true, "person_id": null, "organization_id": "~{\"name\": \"Maura T. Healey\"}"}], "related_bills": [{"identifier": "HD 6138", "legislative_session": "194th", "relation_type": "replaces"}], "versions": [{"note": "Bill Text", "links": [{"url": "https://malegislature.gov/Bills/194/H5429.pdf", "media_type": "application/pdf"}], "date": "", "classification": ""}], "documents": [], "citations": [], "sources": [{"url": "https://malegislature.gov/Bills/194/H5429", "note": ""}], "extras": {}, "jurisdiction": {"id": "ocd-jurisdiction/country:us/state:ma/government", "name": "Massachusetts", "classification": "state", "division_id": "ocd-division/country:us/state:ma"}, "scraped_at": "2026-07-13T22:43:42+00:00", "_id": "4bc9c79a-7f0c-11f1-aa88-e6eb2c01712e"}