{"legislative_session": "194th", "identifier": "H4704", "title": "Amendment H.4704", "from_organization": "~{\"classification\": \"lower\"}", "classification": ["bill"], "subject": [], "abstracts": [{"note": "summary", "abstract": "Text of amendments, recommended by the committee on Ways and Means, to the Senate Bill amending certain laws relative to individuals with disabilities (Senate, No. 2563). November 4, 2025."}], "other_titles": [], "other_identifiers": [], "actions": [{"description": "Text of an amendment, see S2563", "date": "2025-11-05", "organization_id": "~{\"classification\": \"lower\"}", "classification": [], "related_entities": []}], "sponsorships": [{"name": "House Committee on Ways and Means", "classification": "primary", "entity_type": "organization", "primary": true, "person_id": null, "organization_id": "~{\"name\": \"House Committee on Ways and Means\"}"}], "related_bills": [], "versions": [{"note": "Bill Text", "links": [{"url": "https://malegislature.gov/Bills/194/H4704.pdf", "media_type": "application/pdf"}], "date": "", "classification": ""}], "documents": [], "citations": [], "sources": [{"url": "https://malegislature.gov/Bills/194/H4704", "note": ""}], "extras": {}, "jurisdiction": {"id": "ocd-jurisdiction/country:us/state:ma/government", "name": "Massachusetts", "classification": "state", "division_id": "ocd-division/country:us/state:ma"}, "scraped_at": "2025-12-27T09:59:54+00:00", "_id": "caa3ba2e-e30a-11f0-ba98-26d64b42632d"}