{"legislative_session": "194th", "identifier": "S2716", "title": "An Act amending the charter of the town of Rockland", "from_organization": "~{\"classification\": \"upper\"}", "classification": ["bill"], "subject": [], "abstracts": [{"note": "summary", "abstract": "Senate, November 13, 2025 -- The committee on Municipalities and Regional Government to whom was referred the petition (accompanied by bill, Senate, No. 2573) of John F. Keenan (by vote of the town) to amend the charter of the town of Rockland, report the accompanying bill (Senate, No. 2716)."}], "other_titles": [], "other_identifiers": [], "actions": [{"description": "Reported from the committee on Municipalities and Regional Government", "date": "2025-11-13", "organization_id": "~{\"classification\": \"upper\"}", "classification": [], "related_entities": []}, {"description": "New draft of S2573", "date": "2025-11-13", "organization_id": "~{\"classification\": \"upper\"}", "classification": [], "related_entities": []}, {"description": "Bill reported favorably by committee and placed in the Orders of the Day for the next session", "date": "2025-11-13", "organization_id": "~{\"classification\": \"upper\"}", "classification": ["committee-passage-favorable"], "related_entities": []}, {"description": "Taken out of the Orders of the Day", "date": "2025-11-19", "organization_id": "~{\"classification\": \"upper\"}", "classification": [], "related_entities": []}, {"description": "Read second, amended, ordered to a third reading, read third and passed to be engrossed", "date": "2025-11-19", "organization_id": "~{\"classification\": \"upper\"}", "classification": ["passage", "reading-2", "reading-3"], "related_entities": []}, {"description": "Read; and referred to the committee on House Steering, Policy and Scheduling", "date": "2025-11-19", "organization_id": "~{\"classification\": \"lower\"}", "classification": ["referral-committee"], "related_entities": [{"name": "committee on House Steering, Policy and Scheduling", "entity_type": "organization", "organization_id": null}, {"name": "the committee on House Steering, Policy and Scheduling", "entity_type": "organization", "organization_id": null}]}, {"description": "Committee reported that the matter be placed in the Orders of the Day for the next sitting", "date": "2025-11-20", "organization_id": "~{\"classification\": \"lower\"}", "classification": [], "related_entities": []}, {"description": "Rules suspended", "date": "2025-11-20", "organization_id": "~{\"classification\": \"lower\"}", "classification": [], "related_entities": []}, {"description": "Read second and ordered to a third reading", "date": "2025-11-20", "organization_id": "~{\"classification\": \"lower\"}", "classification": ["reading-2"], "related_entities": []}, {"description": "Read third, amended by substitution of a new text (H4866) and passed to be engrossed", "date": "2025-12-18", "organization_id": "~{\"classification\": \"lower\"}", "classification": ["passage", "reading-3"], "related_entities": []}], "sponsorships": [{"name": "Joint Committee on Municipalities and Regional Government", "classification": "primary", "entity_type": "organization", "primary": true, "person_id": null, "organization_id": "~{\"name\": \"Joint Committee on Municipalities and Regional Government\"}"}, {"name": "John F. Keenan", "classification": "cosponsor", "entity_type": "person", "primary": false, "person_id": "~{\"name\": \"John F. Keenan\"}", "organization_id": null}, {"name": "David F. DeCoste", "classification": "cosponsor", "entity_type": "person", "primary": false, "person_id": "~{\"name\": \"David F. DeCoste\"}", "organization_id": null}], "related_bills": [], "versions": [{"note": "Bill Text", "links": [{"url": "https://malegislature.gov/Bills/194/S2716.pdf", "media_type": "application/pdf"}], "date": "", "classification": ""}], "documents": [], "citations": [], "sources": [{"url": "https://malegislature.gov/Bills/194/S2716", "note": ""}], "extras": {}, "jurisdiction": {"id": "ocd-jurisdiction/country:us/state:ma/government", "name": "Massachusetts", "classification": "state", "division_id": "ocd-division/country:us/state:ma"}, "scraped_at": "2026-01-19T10:42:47+00:00", "_id": "97972618-f523-11f0-b005-9aa9e2fb2205"}